keras_convattention/__init__.py
keras_convattention/attention.py
keras_convattention/convattention.py
keras_convattention-0.1.0.dist-info/METADATA
keras_convattention-0.1.0.dist-info/WHEEL
keras_convattention-0.1.0.dist-info/RECORD
